mongo_emb-1.0.0.dist-info/METADATA
mongo_emb-1.0.0.dist-info/WHEEL
mongo_emb/__init__.py
mongo_emb/__pycache__/__init__.cpython-311.pyc
mongo_emb/__pycache__/core.cpython-311.pyc
mongo_emb/core.py
mongo_emb/mongo_emb.pyd
mongo_emb-1.0.0.dist-info/RECORD
