Metadata-Version: 2.4
Name: mongo_emb
Version: 1.0.0
Classifier: Programming Language :: Rust
Classifier: Programming Language :: Python :: Implementation :: CPython
Classifier: Programming Language :: Python :: Implementation :: PyPy
Author-email: Wang Qi <wangmarkqi@gmail.com>
Requires-Python: >=3.8
